perip/psram/psram.v
`timescale 1ns/1ps
/** IS66WVS4M8ALL PSRAM 行为模型
 *
 * 修复:
 *   1. 控制器在 negedge sck 采样 din, 与原模型输出在同一时刻, 存在竞争.
 *      修复: io_out 在 posedge sck 单独更新, 确保数据在控制器采样前稳定.
 *   2. 命令/地址因 1 周期相位偏差产生固定左移:
 *      - 命令: 左移 1 位 (EBh→0xD6, 38h→0x70)
 *      - 地址: 左移 4 位 (一个 nibble)
 *      修复: 命令匹配使用移位值; 地址使用 eff_addr = address>>4.
 *   3. CE# 复位时清除 address/command 寄存器.
 *   4. QPI mode (4-4-4): 上电为 SPI/QSPI 模式, 收到 0x35 命令后切换到 QPI 模式,
 *      在 QPI 模式下命令以 4-bit 传输 (2 个 sck 周期); 收到 0xF5 退出.
 *      QPI 命令相位补偿: S_IDLE 捕获 CMD_LO nibble, 匹配 command[7:4].
 *      地址/数据捕获与 SPI 模式一致 (addr_cnt=0, 相同 nibble 时序).
 */
module psram #(
  parameter ADDR_BITS    = 22,
  parameter DUMMY_CYCLES = 6
)(
  input        sck,
  input        ce_n,
  inout  [3:0] dio
);
  localparam MEM_SIZE       = 1 << ADDR_BITS;
  localparam CMD_CYCLES     = 8;
  localparam CMD_QPI_CYCLES = 2;
  localparam ADDR_CYCLES    = 6;
  localparam DATA_CYCLES    = 8;

  localparam S_IDLE     = 0;
  localparam S_CMD      = 1;
  localparam S_ADDR     = 2;
  localparam S_DUMMY    = 3;
  localparam S_DATA_OUT = 4;
  localparam S_DATA_IN  = 5;

  localparam CMD_EB_SHIFTED = 8'hD6;
  localparam CMD_38_SHIFTED = 8'h70;
  localparam CMD_EBH         = 8'hEB;  // Quad IO Read
  localparam CMD_38H         = 8'h38;  // Quad IO Write
  localparam CMD_35H         = 8'h35;  // Enter QPI mode
  localparam CMD_35_SHIFTED  = 8'h6A;  // 0x35 << 1 (phase shift)
  localparam CMD_F5H         = 8'hF5;  // Exit QPI mode
  localparam CMD_F5_SHIFTED  = 8'hEA;  // 0xF5 << 1 (phase shift)

  reg                 qpi_mode;       // 0=SPI/QSPI, 1=QPI (4-4-4)
  reg [7:0]           memory [0:MEM_SIZE-1];
  reg [3:0]           state;
  reg [7:0]           command;
  reg [ADDR_BITS-1:0] address;
  reg [5:0]           cmd_cnt, addr_cnt, dummy_cnt, data_cnt;
  wire [1:0]          data_idx;

  wire [ADDR_BITS-1:0] eff_addr;
  assign eff_addr = address >> 4;

  reg                 io_oe;
  reg [3:0]           io_out;
  assign dio = io_oe ? io_out : 4'bzzzz;

  wire [7:0] memory_data = memory[eff_addr + data_idx];
  assign data_idx = data_cnt[2:1];

  integer i;
  initial begin
    qpi_mode = 0;
    state = S_IDLE;
    command = 0;
    address = 0;
    cmd_cnt = 0;
    addr_cnt = 0;
    dummy_cnt = 0;
    data_cnt = 0;
    io_oe = 0;
    io_out = 0;
    for (i = 0; i < MEM_SIZE; i = i + 1)
      memory[i] = 0;
  end

  // ---- 主状态机: negedge sck (命令/地址/写数据捕获, 状态转换) ----
  always @(negedge sck or posedge ce_n) begin
    if (ce_n) begin
      state <= S_IDLE; io_oe <= 0; command <= 0; address <= 0;
      cmd_cnt <= 0; addr_cnt <= 0; dummy_cnt <= 0; data_cnt <= 0;
    end
    else begin
      case (state)
        S_IDLE: begin
          if (qpi_mode) begin
            // QPI mode: capture upper nibble (command[7:4])
            command[7:4] <= dio;
            cmd_cnt <= 1; state <= S_CMD;
          end
          else begin
            // SPI mode: capture command MSB
            command <= {7'h0, dio[0]}; cmd_cnt <= 1; state <= S_CMD;
          end
        end
        S_CMD: begin
          if (qpi_mode) begin
            // QPI mode: capture lower nibble (command[3:0])
            command[3:0] <= dio;
            if (cmd_cnt == CMD_QPI_CYCLES - 1) begin
              // 相位补偿: S_IDLE 捕获的是 CMD_LO (bit[3:0]),
              // 因此只匹配 command[7:4] (= CMD_LO nibble) 来识别命令.
              if (command[7:4] == CMD_F5H[3:0] || command[7:4] == CMD_F5_SHIFTED[3:0]) begin
                qpi_mode <= 0; state <= S_IDLE;
              end
              else if (command[7:4] == CMD_EBH[3:0] || command[7:4] == CMD_EB_SHIFTED[3:0] ||
                           command[7:4] == CMD_38H[3:0] || command[7:4] == CMD_38_SHIFTED[3:0]) begin
                addr_cnt <= 0; state <= S_ADDR;
              end
              else
                state <= S_IDLE;
            end
            else begin
              cmd_cnt <= cmd_cnt + 1;
            end
          end
          else begin
            // SPI mode: capture command 1 bit at a time
            command <= {command[6:0], dio[0]};
            if (cmd_cnt == CMD_CYCLES - 1) begin
              if ({command[6:0], dio[0]} == CMD_35H || {command[6:0], dio[0]} == CMD_35_SHIFTED) begin
                qpi_mode <= 1; state <= S_IDLE;
              end
              else begin
                addr_cnt <= 0; state <= S_ADDR;
              end
            end
            else begin
              cmd_cnt <= cmd_cnt + 1;
            end
          end
        end
        S_ADDR: begin
          address[20-(addr_cnt*4)] <= dio[0];
          address[21-(addr_cnt*4)] <= dio[1];
          if (addr_cnt > 0) begin
            address[22-(addr_cnt*4)] <= dio[2];
            address[23-(addr_cnt*4)] <= dio[3];
          end
          if (addr_cnt == ADDR_CYCLES - 1) begin
            if (qpi_mode) begin
              // QPI 模式: 仅匹配 command[7:4] (S_IDLE 捕获的 CMD_LO nibble)
              if (command[7:4] == CMD_EBH[3:0] || command[7:4] == CMD_EB_SHIFTED[3:0]) begin
                dummy_cnt <= 0; state <= S_DUMMY;
              end
              else if (command[7:4] == CMD_38H[3:0] || command[7:4] == CMD_38_SHIFTED[3:0]) begin
                // QPI 写: 在转换周期同时捕获第一个写数据 nibble (D7:4)
                memory[eff_addr][4] <= dio[0];
                memory[eff_addr][5] <= dio[1];
                memory[eff_addr][6] <= dio[2];
                memory[eff_addr][7] <= dio[3];
                data_cnt <= 1;   // 已捕获 upper nibble
                state    <= S_DATA_IN;
              end
              else
                state <= S_IDLE;
            end
          else begin
            if (command == CMD_EBH || command == CMD_EB_SHIFTED) begin
              dummy_cnt <= 0; state <= S_DUMMY;
            end
            else if (command == CMD_38H || command == CMD_38_SHIFTED) begin
              // 关键: 在转换周期同时捕获第一个写数据 nibble (D7:4)
              // 以避免因过渡周期导致数据错位 (nibble swap)
              memory[eff_addr][4] <= dio[0];
              memory[eff_addr][5] <= dio[1];
              memory[eff_addr][6] <= dio[2];
              memory[eff_addr][7] <= dio[3];
              data_cnt <= 1;   // 已捕获 upper nibble
              state    <= S_DATA_IN;
            end
            else state <= S_IDLE;
            end
          end
          else begin
            addr_cnt <= addr_cnt + 1;
          end
        end
        S_DUMMY: begin
          if (dummy_cnt == DUMMY_CYCLES - 1) begin
            if (qpi_mode) begin
              if (command[7:4] == CMD_EBH[3:0] || command[7:4] == CMD_EB_SHIFTED[3:0]) begin
                data_cnt <= 0; io_oe <= 1; state <= S_DATA_OUT;
              end
              else
                state <= S_IDLE;
            end
            else begin
              if (command == CMD_EBH || command == CMD_EB_SHIFTED) begin
                data_cnt <= 0; io_oe <= 1; state <= S_DATA_OUT;
              end
              else
                state <= S_IDLE;
            end
          end else dummy_cnt <= dummy_cnt + 1;
        end
        S_DATA_OUT: begin
          if (data_cnt == DATA_CYCLES) begin
            io_oe <= 0; state <= S_IDLE;
          end
          else data_cnt = data_cnt + 1;
        end
        S_DATA_IN: begin
          if (data_cnt == DATA_CYCLES)
            state <= S_IDLE;
          else begin
            if (data_cnt[0]) begin
              memory[eff_addr + data_idx][0] <= dio[0];
              memory[eff_addr + data_idx][1] <= dio[1];
              memory[eff_addr + data_idx][2] <= dio[2];
              memory[eff_addr + data_idx][3] <= dio[3];
            end
            else begin
              memory[eff_addr + data_idx][4] <= dio[0];
              memory[eff_addr + data_idx][5] <= dio[1];
              memory[eff_addr + data_idx][6] <= dio[2];
              memory[eff_addr + data_idx][7] <= dio[3];
            end
            data_cnt <= data_cnt + 1;
          end
        end
        default: state <= S_IDLE;
      endcase
    end
  end

  // ---- 读数据输出: posedge sck, 在控制器采样前输出 ----
  always @(posedge sck) begin
    if (!ce_n && state == S_DATA_OUT && data_cnt < DATA_CYCLES) begin
      io_out[0] <= data_cnt[0] ? memory_data[0] : memory_data[4];
      io_out[1] <= data_cnt[0] ? memory_data[1] : memory_data[5];
      io_out[2] <= data_cnt[0] ? memory_data[2] : memory_data[6];
      io_out[3] <= data_cnt[0] ? memory_data[3] : memory_data[7];
    end
  end

endmodule

perip-tb/psram/tb_psram.v
`timescale 1ns/1ps

/**
 * IS66WVS4M8ALL PSRAM 行为模型 — 全面测试平台 (iverilog 兼容版)
 *
 * 测试覆盖:
 *   Test 1: Quad IO Read (EBh) — 初始全零内存读取
 *   Test 2: Quad IO Write (38h) + Read back — 数据完整性验证 (多种数据模式)
 *   Test 3: 多地址读写 — 非重叠区域写入/回读，确保各地址独立
 *   Test 4: CE# 复位行为 — CE# 拉高后重新发起操作 / 中途拉高恢复
 *   Test 5: 边界地址 — addr=0 和最大地址
 *   Test 6: 背靠背操作 — 连续快速发起读写
 *
 * 注: 本 testbench 避免使用 unpacked array ports (iverilog 不支持),
 *     所有数据均通过 32-bit packed 向量传递.
 */
module tb_psram;

  // ============================================================
  // 参数定义
  // ============================================================
  localparam CMD_QUAD_IO_READ  = 8'hEB;
  localparam CMD_QUAD_IO_WRITE = 8'h38;
  localparam DUMMY_CLOCKS      = 6;
  localparam CLK_HALF_PERIOD   = 5;    // 10ns 周期 = 100MHz

  // ============================================================
  // 信号声明
  // ============================================================
  reg        sck;
  reg        ce_n;
  wire [3:0] dio;

  reg  [3:0] dio_drive;
  reg        dio_oe;

  assign dio = dio_oe ? dio_drive : 4'bzzzz;

  // ============================================================
  // DUT 实例化
  // ============================================================
  psram dut (
    .sck (sck),
    .ce_n(ce_n),
    .dio (dio)
  );

  // ============================================================
  // 时钟生成
  // ============================================================
  initial sck = 0;
  always #CLK_HALF_PERIOD sck = ~sck;

  // ============================================================
  // 测试变量
  // ============================================================
  reg [31:0] rdata32;     // 读回数据 (byte3, byte2, byte1, byte0)
  reg [31:0] exp32;       // 期望数据
  integer    test_pass;
  integer    test_fail;
  integer    i;

  // ============================================================
  // 底层协议任务
  // ============================================================
  //
  // 时序说明:
  //   PSRAM 模型在 SCK 上升沿采样输入, master 在下降沿切换后续数据.
  //
  // 各阶段消耗的 SCK 周期数 (含内部状态转移):
  //   send_cmd:        9 周期 (8 位命令 + 1 转移)
  //   send_addr:       7 周期 (6 四线地址拍 + 1 转移)
  //   wait_dummy(n):   n+1 周期 (n dummy + 1 转移到 S_DATA_OUT)
  //   recv_data:       9 周期 (8 四线数据拍 + 1 转移到 S_IDLE)
  //   send_data:       9 周期 (同上)
  //

  // --- 发送 8 位命令 (串行 SIO[0], MSB 优先) ---
  task psram_send_cmd;
    input [7:0] cmd;
    integer j;
    begin
      @(negedge sck);
      ce_n = 0;
      dio_oe = 1;
      dio_drive = {3'b000, cmd[7]};
      @(posedge sck);

      for (j = 6; j >= 0; j = j - 1) begin
        @(negedge sck);
        dio_drive = {3'b000, cmd[j]};
        @(posedge sck);
      end
    end
  endtask

  // --- 发送 24 位地址 (四线 SIO[3:0], MS nibble 优先) ---
  task psram_send_addr;
    input [23:0] addr;
    integer j;
      begin
      for (j = 5; j >= 0; j = j - 1) begin
        @(negedge sck);
        dio_drive = addr[j*4 +: 4];
        @(posedge sck);
      end
    end
  endtask

  // --- 等待 N 个 dummy 周期 (+1 转移周期), dio 高阻 ---
  task psram_wait_dummy;
    input [5:0] n;
    begin
      dio_oe = 0;
      repeat (n + 1) @(posedge sck);
    end
  endtask

  // --- 接收 4 字节读数据 (四线) → 32-bit packed ---
  //     字节映射: data[ 7: 0] = byte0, data[15: 8] = byte1,
  //               data[23:16] = byte2, data[31:24] = byte3
  task psram_recv_data;
    output [31:0] data;
    integer j;
    reg [31:0] tmp;
    reg [3:0]  nibble;
    begin
      dio_oe = 0;
      tmp = 0;
      for (j = 0; j < 4; j = j + 1) begin
        @(posedge sck);
        nibble = dio;               // 高半字节 [7:4]
        tmp[j*8+4 +: 4] = nibble;
        @(posedge sck);
        nibble = dio;               // 低半字节 [3:0]
        tmp[j*8 +: 4] = nibble;
      end
      @(posedge sck);    // 转移: PSRAM → S_IDLE
      data = tmp;
    end
  endtask

  // --- 发送 4 字节写数据 (四线) ---
  task psram_send_data;
    input [31:0] data;
    integer j;
    begin
      @(negedge sck);
      dio_oe = 1;
      dio_drive = data[7:4];
      @(posedge sck);
      for (j = 0; j < 4; j = j + 1) begin
        @(negedge sck);
        dio_drive = data[j*8 +: 4];
        @(posedge sck);
        if (j < 3) begin
          @(negedge sck);
          dio_drive = data[(j+1)*8+4 +: 4];
          @(posedge sck);
        end
      end
      @(negedge sck);
    end
  endtask

  // --- 结束操作: CE# 拉高, 释放 dio ---
  task psram_end_op;
    begin
      dio_oe = 0;
      ce_n = 1;
      @(posedge sck);    // tCPH ≥ 1 SCK
    end
  endtask

  // ============================================================
  // 高层测试原语
  // ============================================================

  // --- Quad IO Read + 自动比对 ---
  task test_quad_read;
    input [23:0]       addr;
    input [31:0]       exp;
    input [8*32-1:0]   test_name;
    integer j;
    reg    mismatch;
    begin
      $display("  [TEST] %0s: Quad IO Read @ addr=0x%06h", test_name, addr);
      psram_send_cmd(CMD_QUAD_IO_READ);
      psram_send_addr(addr);
      psram_wait_dummy(DUMMY_CLOCKS);
      psram_recv_data(rdata32);
      psram_end_op();

      if (rdata32 !== exp) begin
        mismatch = 1;
        for (j = 0; j < 4; j = j + 1) begin
          if (rdata32[j*8 +: 8] !== exp[j*8 +: 8]) begin
            $error("    FAIL: byte[%0d] read=0x%02h, expected=0x%02h",
                   j, rdata32[j*8 +: 8], exp[j*8 +: 8]);
          end
        end
        test_fail = test_fail + 1;
      end else begin
        $display("    PASS");
        test_pass = test_pass + 1;
      end
    end
  endtask

  // --- Quad IO Write + Read-back + 自动比对 ---
  task test_write_read;
    input [23:0]       addr;
    input [31:0]       wdata;
    input [8*32-1:0]   test_name;
    integer j;
    reg    mismatch;
    begin
      $display("  [TEST] %0s: Write-then-Read @ addr=0x%06h", test_name, addr);

      // Write
      psram_send_cmd(CMD_QUAD_IO_WRITE);
      psram_send_addr(addr);
      psram_send_data(wdata);
      psram_end_op();

      // Read back
      psram_send_cmd(CMD_QUAD_IO_READ);
      psram_send_addr(addr);
      psram_wait_dummy(DUMMY_CLOCKS);
      psram_recv_data(rdata32);
      psram_end_op();

      if (rdata32 !== wdata) begin
        mismatch = 1;
        for (j = 0; j < 4; j = j + 1) begin
          if (rdata32[j*8 +: 8] !== wdata[j*8 +: 8]) begin
            $error("    FAIL: byte[%0d] read=0x%02h, expected=0x%02h",
                   j, rdata32[j*8 +: 8], wdata[j*8 +: 8]);
          end
        end
        test_fail = test_fail + 1;
      end else begin
        $display("    PASS");
        test_pass = test_pass + 1;
      end
    end
  endtask

  // ============================================================
  // 主测试序列
  // ============================================================
  initial begin
    $dumpfile("tb_psram.vcd");
    $dumpvars(0, tb_psram);

    sck        = 0;
    ce_n       = 1;
    dio_oe     = 0;
    dio_drive  = 0;
    test_pass  = 0;
    test_fail  = 0;

    repeat(4) @(posedge sck);

    $display("==============================================");
    $display(" PSRAM Behavioral Model Test Suite");
    $display(" IS66WVS4M8ALL - SPI Quad IO (EBh/38h)");
    $display(" SCK = 100 MHz (10 ns period)");
    $display("==============================================");

    // --------------------------------------------------------
    // Test 1: 读取初始全零内存
    // --------------------------------------------------------
    $display("\n=== Test 1: Read default (all-zero) memory ===");
    exp32 = 32'h00000000;
    test_quad_read(24'h000000, exp32, "addr=0x000000");
    test_quad_read(24'h001000, exp32, "addr=0x001000");
    test_quad_read(24'h3FFFFC, exp32, "addr=0x3FFFFC (last 4B)");

    // --------------------------------------------------------
    // Test 2: 写入 + 读出验证 (多种数据模式)
    // --------------------------------------------------------
    $display("\n=== Test 2: Write + Read-back (data patterns) ===");

    // 2a: Walking ones (byte0=0x01, byte1=0x02, byte2=0x04, byte3=0x08)
    exp32 = {8'h08, 8'h04, 8'h02, 8'h01};
    test_write_read(24'h000100, exp32, "Walking ones");

    // 2b: 0x55 / 0xAA 交替
    exp32 = {8'hAA, 8'h55, 8'hAA, 8'h55};
    test_write_read(24'h000104, exp32, "0x55/0xAA alternating");

    // 2c: 全 1
    test_write_read(24'h000108, 32'hFFFFFFFF, "All-ones (0xFF)");

    // 2d: 全 0 覆盖
    test_write_read(24'h00010C, 32'h00000000, "All-zeros overwrite");

    // 2e: 递增
    exp32 = {8'hA3, 8'hA2, 8'hA1, 8'hA0};
    test_write_read(24'h000110, exp32, "Incrementing (0xA0-0xA3)");

    // 2f: 递减
    exp32 = {8'hED, 8'hEE, 8'hEF, 8'hF0};
    test_write_read(24'h000114, exp32, "Decrementing (0xF0-0xED)");

    // --------------------------------------------------------
    // Test 3: 多地址独立读写
    // --------------------------------------------------------
    $display("\n=== Test 3: Multi-address independence ===");

    // Write A
    exp32 = {8'hA3, 8'hA2, 8'hA1, 8'hA0};
    test_write_read(24'h002000, exp32, "Write+Read addr=0x2000");

    // Write B
    exp32 = {8'hB3, 8'hB2, 8'hB1, 8'hB0};
    test_write_read(24'h003000, exp32, "Write+Read addr=0x3000");

    // Write C (紧接 A 之后)
    exp32 = {8'hC3, 8'hC2, 8'hC1, 8'hC0};
    test_write_read(24'h002004, exp32, "Write+Read addr=0x2004");

    // 回读 A — 确保未被破坏
    exp32 = {8'hA3, 8'hA2, 8'hA1, 8'hA0};
    test_quad_read(24'h002000, exp32, "Re-read addr=0x2000 (A)");

    // 回读 B
    exp32 = {8'hB3, 8'hB2, 8'hB1, 8'hB0};
    test_quad_read(24'h003000, exp32, "Re-read addr=0x3000 (B)");

    // 回读 C
    exp32 = {8'hC3, 8'hC2, 8'hC1, 8'hC0};
    test_quad_read(24'h002004, exp32, "Re-read addr=0x2004 (C)");

    // --------------------------------------------------------
    // Test 4: CE# 复位行为
    // --------------------------------------------------------
    $display("\n=== Test 4: CE# reset behavior ===");

    // 4a: 正常 Write+Read, CE# 拉高后重新操作
    exp32 = {8'hDE, 8'hDD, 8'hDC, 8'hDB};
    test_write_read(24'h000400, exp32, "Normal CE# cycle");

    // 4b: 写入中途 CE# 拉高 (异常终止), 再重新写入
    begin
      $display("  [TEST] CE# abort during write, then re-write @ addr=0x000404");
      // 发起写操作
      psram_send_cmd(CMD_QUAD_IO_WRITE);
      psram_send_addr(24'h000404);
      // 写两个字节 (byte0=0x11, byte1=0x22)
      dio_oe = 1;
      dio_drive = 4'h1;  // byte0 upper, drive before @
      @(posedge sck);
      dio_drive = 4'h1;  // byte0 lower
      @(posedge sck);
      dio_drive = 4'h2;  // byte1 upper
      @(posedge sck);
      dio_drive = 4'h2;  // byte1 lower
      @(posedge sck);
      // 中途拉高 CE# (模拟异常)
      ce_n = 1;
      dio_oe = 0;
      repeat(3) @(posedge sck);

      // 重新完整写入
      exp32 = {8'h5D, 8'h5C, 8'h5B, 8'h5A};
      psram_send_cmd(CMD_QUAD_IO_WRITE);
      psram_send_addr(24'h000404);
      psram_send_data(exp32);
      psram_end_op();

      // 回读验证
      psram_send_cmd(CMD_QUAD_IO_READ);
      psram_send_addr(24'h000404);
      psram_wait_dummy(DUMMY_CLOCKS);
      psram_recv_data(rdata32);
      psram_end_op();

      if (rdata32 !== exp32) begin
        $error("    FAIL: CE# abort recovery mismatch");
        $display("      read=0x%08h, expected=0x%08h", rdata32, exp32);
        test_fail = test_fail + 1;
      end else begin
        $display("    PASS: CE# abort recovery OK");
        test_pass = test_pass + 1;
      end
    end

    // 4c: 快速 CE# 翻转 (模拟噪声/毛刺)
    begin
      $display("  [TEST] CE# glitch resilience @ addr=0x000500");
      exp32 = {8'hCE, 8'hCD, 8'hCC, 8'hCB};
      // 写入
      psram_send_cmd(CMD_QUAD_IO_WRITE);
      psram_send_addr(24'h000500);
      psram_send_data(exp32);
      psram_end_op();

      // 快速 CE# 翻转
      ce_n = 1; @(posedge sck); @(posedge sck);
      ce_n = 0; @(posedge sck); ce_n = 1; @(posedge sck);
      ce_n = 0; @(posedge sck); ce_n = 1;
      repeat(3) @(posedge sck);

      // 回读
      psram_send_cmd(CMD_QUAD_IO_READ);
      psram_send_addr(24'h000500);
      psram_wait_dummy(DUMMY_CLOCKS);
      psram_recv_data(rdata32);
      psram_end_op();

      if (rdata32 !== exp32) begin
        $error("    FAIL: data corrupted by CE# glitches");
        test_fail = test_fail + 1;
      end else begin
        $display("    PASS: data intact after CE# glitches");
        test_pass = test_pass + 1;
      end
    end

    // --------------------------------------------------------
    // Test 5: 边界地址
    // --------------------------------------------------------
    $display("\n=== Test 5: Boundary address tests ===");

    // 地址 0 — 之前未写入，仍为初始值 0x00
    exp32 = 32'h00000000;
    test_quad_read(24'h000000, exp32, "addr=0 (boundary, all-zero)");

    // 最大地址 (4MB - 4)
    exp32 = {8'hF0, 8'hEF, 8'hEE, 8'hED};
    test_write_read(24'h3FFFFC, exp32, "addr=0x3FFFFC (max-4B)");

    // --------------------------------------------------------
    // Test 6: 背靠背操作
    // --------------------------------------------------------
    $display("\n=== Test 6: Back-to-back operations ===");
    begin
      reg [31:0] w1, w2;
      w1 = {8'h14, 8'h13, 8'h12, 8'h11};
      w2 = {8'h24, 8'h23, 8'h22, 8'h21};

      // 连续两次 Write
      $display("  [TEST] Back-to-back writes @ addr=0x600 and 0x604");
      psram_send_cmd(CMD_QUAD_IO_WRITE);
      psram_send_addr(24'h000600);
      psram_send_data(w1);
      psram_end_op();

      psram_send_cmd(CMD_QUAD_IO_WRITE);
      psram_send_addr(24'h000604);
      psram_send_data(w2);
      psram_end_op();

      // 连续两次 Read
      $display("  [TEST] Back-to-back reads");
      psram_send_cmd(CMD_QUAD_IO_READ);
      psram_send_addr(24'h000600);
      psram_wait_dummy(DUMMY_CLOCKS);
      psram_recv_data(rdata32);
      psram_end_op();

      if (rdata32 !== w1) begin
        $error("    FAIL: Read A mismatch (0x%08h vs 0x%08h)", rdata32, w1);
        test_fail = test_fail + 1;
      end else begin
        $display("    Read A (0x600): PASS");
        test_pass = test_pass + 1;
      end

      psram_send_cmd(CMD_QUAD_IO_READ);
      psram_send_addr(24'h000604);
      psram_wait_dummy(DUMMY_CLOCKS);
      psram_recv_data(rdata32);
      psram_end_op();

      if (rdata32 !== w2) begin
        $error("    FAIL: Read B mismatch (0x%08h vs 0x%08h)", rdata32, w2);
        test_fail = test_fail + 1;
      end else begin
        $display("    Read B (0x604): PASS");
        test_pass = test_pass + 1;
      end

      // 背靠背 Read 然后 Write
      $display("  [TEST] Read-then-Write @ addr=0x600");
      psram_send_cmd(CMD_QUAD_IO_READ);
      psram_send_addr(24'h000600);
      psram_wait_dummy(DUMMY_CLOCKS);
      psram_recv_data(rdata32);
      psram_end_op();

      exp32 = {8'h34, 8'h33, 8'h32, 8'h31};
      psram_send_cmd(CMD_QUAD_IO_WRITE);
      psram_send_addr(24'h000600);
      psram_send_data(exp32);
      psram_end_op();

      test_quad_read(24'h000600, exp32, "Verify after read-then-write");
    end

    // ============================================================
    // 测试总结
    // ============================================================
    $display("\n==============================================");
    $display(" TEST SUMMARY");
    $display("   Total passed: %0d", test_pass);
    $display("   Total failed: %0d", test_fail);
    if (test_fail == 0) begin
      $display("   RESULT: ALL TESTS PASSED");
    end else begin
      $display("   RESULT: %0d TEST(S) FAILED!", test_fail);
    end
    $display("==============================================");

    #200;
    $finish;
  end

endmodule

perip-tb/psram/tb_psram.vcd
$date
	Sat Jul  4 18:28:44 2026
$end
$version
	Icarus Verilog
$end
$timescale
	1ps
$end
$scope module tb_psram $end
$var wire 4 ! dio [3:0] $end
$var parameter 32 " CLK_HALF_PERIOD $end
$var parameter 8 # CMD_QUAD_IO_READ $end
$var parameter 8 $ CMD_QUAD_IO_WRITE $end
$var parameter 32 % DUMMY_CLOCKS $end
$var reg 1 & ce_n $end
$var reg 4 ' dio_drive [3:0] $end
$var reg 1 ( dio_oe $end
$var reg 32 ) exp32 [31:0] $end
$var reg 32 * rdata32 [31:0] $end
$var reg 1 + sck $end
$var integer 32 , test_fail [31:0] $end
$var integer 32 - test_pass [31:0] $end
$scope module dut $end
$var wire 1 & ce_n $end
$var wire 4 . dio [3:0] $end
$var wire 8 / memory_data [7:0] $end
$var wire 1 + sck $end
$var wire 22 0 eff_addr [21:0] $end
$var wire 2 1 data_idx [1:0] $end
$var parameter 32 2 ADDR_BITS $end
$var parameter 32 3 ADDR_CYCLES $end
$var parameter 8 4 CMD_35H $end
$var parameter 8 5 CMD_35_SHIFTED $end
$var parameter 8 6 CMD_38H $end
$var parameter 8 7 CMD_38_SHIFTED $end
$var parameter 32 8 CMD_CYCLES $end
$var parameter 8 9 CMD_EBH $end
$var parameter 8 : CMD_EB_SHIFTED $end
$var parameter 8 ; CMD_F5H $end
$var parameter 8 < CMD_F5_SHIFTED $end
$var parameter 32 = CMD_QPI_CYCLES $end
$var parameter 32 > DATA_CYCLES $end
$var parameter 32 ? DUMMY_CYCLES $end
$var parameter 54 @ MEM_SIZE $end
$var parameter 32 A S_ADDR $end
$var parameter 32 B S_CMD $end
$var parameter 32 C S_DATA_IN $end
$var parameter 32 D S_DATA_OUT $end
$var parameter 32 E S_DUMMY $end
$var parameter 32 F S_IDLE $end
$var reg 6 G addr_cnt [5:0] $end
$var reg 22 H address [21:0] $end
$var reg 6 I cmd_cnt [5:0] $end
$var reg 8 J command [7:0] $end
$var reg 6 K data_cnt [5:0] $end
$var reg 6 L dummy_cnt [5:0] $end
$var reg 1 M io_oe $end
$var reg 4 N io_out [3:0] $end
$var reg 1 O qpi_mode $end
$var reg 4 P state [3:0] $end
$var integer 32 Q i [31:0] $end
$upscope $end
$scope begin $unm_blk_76 $end
$var reg 32 R w1 [31:0] $end
$var reg 32 S w2 [31:0] $end
$upscope $end
$scope task psram_end_op $end
$upscope $end
$scope task psram_recv_data $end
$var reg 32 T data [31:0] $end
$var reg 4 U nibble [3:0] $end
$var reg 32 V tmp [31:0] $end
$var integer 32 W j [31:0] $end
$upscope $end
$scope task psram_send_addr $end
$var reg 24 X addr [23:0] $end
$var integer 32 Y j [31:0] $end
$upscope $end
$scope task psram_send_cmd $end
$var reg 8 Z cmd [7:0] $end
$var integer 32 [ j [31:0] $end
$upscope $end
$scope task psram_send_data $end
$var reg 32 \ data [31:0] $end
$var integer 32 ] j [31:0] $end
$upscope $end
$scope task psram_wait_dummy $end
$var reg 6 ^ n [5:0] $end
$upscope $end
$scope task test_quad_read $end
$var reg 24 _ addr [23:0] $end
$var reg 32 ` exp [31:0] $end
$var reg 1 a mismatch $end
$var reg 256 b test_name [255:0] $end
$var integer 32 c j [31:0] $end
$upscope $end
$scope task test_write_read $end
$var reg 24 d addr [23:0] $end
$var reg 1 e mismatch $end
$var reg 256 f test_name [255:0] $end
$var reg 32 g wdata [31:0] $end
$var integer 32 h j [31:0] $end
$upscope $end
$upscope $end
$enddefinitions $end
$comment Show the parameter values. $end
$dumpall
b0 F
b11 E
b100 D
b101 C
b1 B
b10 A
b10000000000000000000000 @
b110 ?
b1000 >
b10 =
b11101010 <
b11110101 ;
b11010110 :
b11101011 9
b1000 8
b1110000 7
b111000 6
b1101010 5
b110101 4
b110 3
b10110 2
b110 %
b111000 $
b11101011 #
b101 "
$end
#0
$dumpvars
bx h
bx g
bx f
xe
bx d
bx c
bx b
xa
bx `
bx _
bx ^
bx ]
bx \
bx [
bx Z
bx Y
bx X
bx W
bx V
bx U
bx T
bx S
bx R
b10000000000000000000000 Q
b0 P
0O
b0 N
0M
b0 L
b0 K
b0 J
b0 I
b0 H
b0 G
b0 1
b0 0
b0 /
bz .
b0 -
b0 ,
0+
bx *
bx )
0(
b0 '
1&
bz !
$end
#5000
1+
#10000
0+
#15000
1+
#20000
0+
#25000
1+
#30000
0+
#35000
b11101011 Z
b1100001011001000110010001110010001111010011000001111000001100000011000000110000001100000011000000110000 b
b0 `
b0 _
b0 )
1+
#40000
b1 !
b1 .
b1 '
1(
0&
0+
#45000
b1 P
b1 I
b1 J
b110 [
1+
#50000
0+
#55000
b10 I
b11 J
b101 [
1+
#60000
0+
#65000
b11 I
b111 J
b100 [
1+
#70000
b0 !
b0 .
b0 '
0+
#75000
b100 I
b1110 J
b11 [
1+
#80000
b1 !
b1 .
b1 '
0+
#85000
b101 I
b11101 J
b10 [
1+
#90000
b0 !
b0 .
b0 '
0+
#95000
b110 I
b111010 J
b1 [
1+
#100000
b1 !
b1 .
b1 '
0+
#105000
b111 I
b1110101 J
b0 [
1+
#110000
0+
#115000
b10 P
b11101011 J
b0 X
b11111111111111111111111111111111 [
1+
#120000
b101 Y
0+
#125000
b10000000000000000 0
b1 G
b100000000000000000000 H
1+
#130000
b0 !
b0 .
b0 '
0+
#135000
b10 G
b100 Y
1+
#140000
0+
#145000
b11 G
b11 Y
1+
#150000
0+
#155000
b100 G
b10 Y
1+
#160000
0+
#165000
b101 G
b1 Y
1+
#170000
0+
#175000
b11 P
b0 Y
1+
#180000
0+
#185000
b1 L
bz !
bz .
0(
b110 ^
b11111111111111111111111111111111 Y
1+
#190000
0+
#195000
b10 L
1+
#200000
0+
#205000
b11 L
1+
#210000
0+
#215000
b100 L
1+
#220000
0+
#225000
b101 L
1+
#230000
0+
#235000
b0 !
b0 .
b100 P
1M
1+
#240000
0+
#245000
b1 K
1+
#250000
0+
#255000
b1 1
b10 K
b0 W
b0 V
1+
#260000
0+
#265000
b11 K
b0 U
1+
#270000
0+
#275000
b10 1
b100 K
b1 W
1+
#280000
0+
#285000
b101 K
1+
#290000
0+
#295000
b11 1
b110 K
b10 W
1+
#300000
0+
#305000
b111 K
1+
#310000
0+
#315000
b0 1
b1000 K
b11 W
1+
#320000
0+
#325000
bz !
bz .
b0 P
0M
1+
#330000
0+
